{"Printers":[{"name":"ESCOLARIDADE","marca":"Lexmark","modelo":"MX622adhe","status":"Online","url":"http://150.161.80.15","serial":"7018840002TB3","totalImpressoes":121182,"tonerObj":{"nivelToner":6,"statusToner":"OK","corToner":"Black","serialToner":"CAB220392B04","pagRestantesToner":1900},"unidade":{"nivelUnidade":73,"corUnidade":"Black","serialUnidade":"CAD212777542","statusUnidade":"OK","pagRestantesUnidade":60000},"kitManutecao":{"pagRestantesKit":78900,"statuskit":"OK","serialKit":"LEX26F121251","nivelKit":40},"estilo":{"cssNivel":"progress-bar progress-bar-striped bg-danger","cssKit":"progress-bar progress-bar-striped bg-warning","cssUnidade":"progress-bar progress-bar-striped bg-info","cssName":"list-group-item list-group-item-success","cssStatusToner":"badge badge-success","cssStatusUnidade":"badge badge-success","cssStatusKit":"badge badge-success"},"ocorrencias":[]},{"name":"INFRA","marca":"Lexmark","modelo":"MX622adhe","status":"Online","url":"http://150.161.81.6","serial":"7018841002W45","totalImpressoes":27967,"tonerObj":{"nivelToner":12,"statusToner":"OK","corToner":"Black","serialToner":"CAB19074345F","pagRestantesToner":3300},"unidade":{"nivelUnidade":100,"corUnidade":"Black","serialUnidade":"CAD2127775E7","statusUnidade":"OK","pagRestantesUnidade":60000},"kitManutecao":{"pagRestantesKit":172100,"statuskit":"OK","serialKit":"LEX26F28039","nivelKit":87},"estilo":{"cssNivel":"progress-bar progress-bar-striped bg-danger","cssKit":"progress-bar progress-bar-striped bg-success","cssUnidade":"progress-bar progress-bar-striped bg-success","cssName":"list-group-item list-group-item-success","cssStatusToner":"badge badge-success","cssStatusUnidade":"badge badge-success","cssStatusKit":"badge badge-success"},"ocorrencias":[]},{"name":"SGP","marca":"Lexmark","modelo":"MX622adhe","status":"Online","url":"http://150.161.80.5","serial":"7018840002TCD","totalImpressoes":21358,"tonerObj":{"nivelToner":34,"statusToner":"OK","corToner":"Black","serialToner":"CAB190743E4A","pagRestantesToner":8100},"unidade":{"nivelUnidade":65,"corUnidade":"Black","serialUnidade":"CAD18247200C","statusUnidade":"OK","pagRestantesUnidade":60000},"kitManutecao":{"pagRestantesKit":178700,"statuskit":"OK","serialKit":"LEX26F21408","nivelKit":90},"estilo":{"cssNivel":"progress-bar progress-bar-striped bg-warning","cssKit":"progress-bar progress-bar-striped bg-success","cssUnidade":"progress-bar progress-bar-striped bg-info","cssName":"list-group-item list-group-item-success","cssStatusToner":"badge badge-success","cssStatusUnidade":"badge badge-success","cssStatusKit":"badge badge-success"},"ocorrencias":[]},{"name":"BIBLIOTECA","marca":"Lexmark","modelo":"MX622adhe","status":"Online","url":"http://150.161.80.8","serial":"7018841002W8X","totalImpressoes":14032,"tonerObj":{"nivelToner":49,"statusToner":"OK","corToner":"Black","serialToner":"CAB2003139D1","pagRestantesToner":8200},"unidade":{"nivelUnidade":76,"corUnidade":"Black","serialUnidade":"CAD182783CE6","statusUnidade":"OK","pagRestantesUnidade":60000},"kitManutecao":{"pagRestantesKit":178700,"statuskit":"OK","serialKit":"LEX26F14091","nivelKit":93},"estilo":{"cssNivel":"progress-bar progress-bar-striped bg-warning","cssKit":"progress-bar progress-bar-striped bg-success","cssUnidade":"progress-bar progress-bar-striped bg-success","cssName":"list-group-item list-group-item-success","cssStatusToner":"badge badge-success","cssStatusUnidade":"badge badge-success","cssStatusKit":"badge badge-success"},"ocorrencias":[]},{"name":"ESCOLARIDADE_PROFESSORES","marca":"Lexmark","modelo":"MX910de","status":"Online","url":"http://150.161.80.9","serial":"7421013003914","totalImpressoes":121120,"tonerObj":{"nivelToner":49,"statusToner":"OK","corToner":"black","pagRestantesToner":32500},"unidade":{"nivelUnidade":81,"corUnidade":"black","statusUnidade":"OK"},"kitManutecao":{"statuskit":"OK","nivelKit":100},"estilo":{"cssNivel":"progress-bar progress-bar-striped bg-warning","cssKit":"progress-bar progress-bar-striped bg-success","cssUnidade":"progress-bar progress-bar-striped bg-success","cssName":"list-group-item list-group-item-success","cssStatusToner":"badge badge-success","cssStatusUnidade":"badge badge-success","cssStatusKit":"badge badge-success"},"ocorrencias":[{"printerSerial":"7421013003914","mensagem":"Impressora Carregada","tipo":"impressora","timeStamp":"Jul 12, 2023, 9:36:39 AM","status":"Em Aberto"},{"printerSerial":"7421013003914","mensagem":"impressora carregada do Json","tipo":"impressora","timeStamp":"Jul 12, 2023, 9:37:49 AM","status":"Em Aberto"},{"printerSerial":"7421013003914","mensagem":"impressora carregada do Json","tipo":"impressora","timeStamp":"Jul 12, 2023, 9:42:41 AM","status":"Em Aberto"},{"printerSerial":"7421013003914","mensagem":"impressora carregada do Json","tipo":"impressora","timeStamp":"Jul 12, 2023, 9:43:57 AM","status":"Em Aberto"},{"printerSerial":"7421013003914","mensagem":"impressora carregada do Json","tipo":"impressora","timeStamp":"Jul 12, 2023, 9:48:49 AM","status":"Em Aberto"},{"printerSerial":"7421013003914","mensagem":"impressora carregada do Json","tipo":"impressora","timeStamp":"Jul 12, 2023, 9:50:06 AM","status":"Em Aberto"},{"printerSerial":"7421013003914","mensagem":"impressora carregada do Json","tipo":"impressora","timeStamp":"Jul 12, 2023, 9:54:57 AM","status":"Em Aberto"},{"printerSerial":"7421013003914","mensagem":"impressora carregada do Json","tipo":"impressora","timeStamp":"Jul 12, 2023, 9:56:14 AM","status":"Em Aberto"},{"printerSerial":"7421013003914","mensagem":"impressora carregada do Json","tipo":"impressora","timeStamp":"Jul 12, 2023, 10:01:05 AM","status":"Em Aberto"},{"printerSerial":"7421013003914","mensagem":"impressora carregada do Json","tipo":"impressora","timeStamp":"Jul 12, 2023, 10:02:21 AM","status":"Em Aberto"},{"printerSerial":"7421013003914","mensagem":"impressora carregada do Json","tipo":"impressora","timeStamp":"Jul 12, 2023, 10:07:13 AM","status":"Em Aberto"},{"printerSerial":"7421013003914","mensagem":"impressora carregada do Json","tipo":"impressora","timeStamp":"Jul 12, 2023, 10:08:29 AM","status":"Em Aberto"},{"printerSerial":"7421013003914","mensagem":"impressora carregada do Json","tipo":"impressora","timeStamp":"Jul 12, 2023, 10:13:22 AM","status":"Em Aberto"},{"printerSerial":"7421013003914","mensagem":"impressora carregada do Json","tipo":"impressora","timeStamp":"Jul 12, 2023, 10:14:37 AM","status":"Em Aberto"},{"printerSerial":"7421013003914","mensagem":"impressora carregada do Json","tipo":"impressora","timeStamp":"Jul 12, 2023, 10:19:30 AM","status":"Em Aberto"},{"printerSerial":"7421013003914","mensagem":"impressora carregada do Json","tipo":"impressora","timeStamp":"Jul 12, 2023, 10:20:03 AM","status":"Em Aberto"},{"printerSerial":"7421013003914","mensagem":"impressora carregada do Json","tipo":"impressora","timeStamp":"Jul 12, 2023, 10:20:34 AM","status":"Em Aberto"},{"printerSerial":"7421013003914","mensagem":"impressora carregada do Json","tipo":"impressora","timeStamp":"Jul 12, 2023, 10:20:48 AM","status":"Em Aberto"},{"printerSerial":"7421013003914","mensagem":"impressora carregada do Json","tipo":"impressora","timeStamp":"Jul 12, 2023, 10:25:39 AM","status":"Em Aberto"},{"printerSerial":"7421013003914","mensagem":"impressora carregada do Json","tipo":"impressora","timeStamp":"Jul 12, 2023, 10:26:55 AM","status":"Em Aberto"},{"printerSerial":"7421013003914","mensagem":"impressora carregada do Json","tipo":"impressora","timeStamp":"Jul 12, 2023, 10:34:16 AM","status":"Em Aberto"},{"printerSerial":"7421013003914","mensagem":"impressora carregada do Json","tipo":"impressora","timeStamp":"Jul 12, 2023, 10:34:57 AM","status":"Em Aberto"},{"printerSerial":"7421013003914","mensagem":"impressora carregada do Json","tipo":"impressora","timeStamp":"Jul 12, 2023, 10:37:34 AM","status":"Em Aberto"},{"printerSerial":"7421013003914","mensagem":"impressora carregada do Json","tipo":"impressora","timeStamp":"Jul 12, 2023, 10:38:52 AM","status":"Em Aberto"},{"printerSerial":"7421013003914","mensagem":"impressora carregada do Json","tipo":"impressora","timeStamp":"Jul 12, 2023, 10:44:59 AM","status":"Em Aberto"},{"printerSerial":"7421013003914","mensagem":"impressora carregada do Json","tipo":"impressora","timeStamp":"Jul 12, 2023, 10:49:39 AM","status":"Em Aberto"},{"printerSerial":"7421013003914","mensagem":"impressora carregada do Json","tipo":"impressora","timeStamp":"Jul 12, 2023, 10:53:33 AM","status":"Em Aberto"},{"printerSerial":"7421013003914","mensagem":"impressora carregada do Json","tipo":"impressora","timeStamp":"Jul 12, 2023, 10:55:15 AM","status":"Em Aberto"},{"printerSerial":"7421013003914","mensagem":"impressora carregada do Json","tipo":"impressora","timeStamp":"Jul 12, 2023, 10:58:10 AM","status":"Em Aberto"},{"printerSerial":"7421013003914","mensagem":"impressora carregada do Json","tipo":"impressora","timeStamp":"Jul 12, 2023, 10:58:18 AM","status":"Em Aberto"},{"printerSerial":"7421013003914","mensagem":"impressora carregada do Json","tipo":"impressora","timeStamp":"Jul 12, 2023, 10:59:09 AM","status":"Em Aberto"},{"printerSerial":"7421013003914","mensagem":"impressora carregada do Json","tipo":"impressora","timeStamp":"Jul 12, 2023, 11:05:16 AM","status":"Em Aberto"},{"printerSerial":"7421013003914","mensagem":"impressora carregada do Json","tipo":"impressora","timeStamp":"Jul 12, 2023, 11:11:24 AM","status":"Em Aberto"},{"printerSerial":"7421013003914","mensagem":"impressora carregada do Json","tipo":"impressora","timeStamp":"Jul 12, 2023, 11:17:33 AM","status":"Em Aberto"},{"printerSerial":"7421013003914","mensagem":"impressora carregada do Json","tipo":"impressora","timeStamp":"Jul 12, 2023, 11:23:41 AM","status":"Em Aberto"},{"printerSerial":"7421013003914","mensagem":"impressora carregada do Json","tipo":"impressora","timeStamp":"Jul 12, 2023, 11:29:49 AM","status":"Em Aberto"},{"printerSerial":"7421013003914","mensagem":"impressora carregada do Json","tipo":"impressora","timeStamp":"Jul 12, 2023, 11:35:57 AM","status":"Em Aberto"},{"printerSerial":"7421013003914","mensagem":"impressora carregada do Json","tipo":"impressora","timeStamp":"Jul 12, 2023, 11:42:05 AM","status":"Em Aberto"},{"printerSerial":"7421013003914","mensagem":"impressora carregada do Json","tipo":"impressora","timeStamp":"Jul 12, 2023, 11:48:13 AM","status":"Em Aberto"},{"printerSerial":"7421013003914","mensagem":"impressora carregada do Json","tipo":"impressora","timeStamp":"Jul 12, 2023, 11:54:21 AM","status":"Em Aberto"},{"printerSerial":"7421013003914","mensagem":"impressora carregada do Json","tipo":"impressora","timeStamp":"Jul 12, 2023, 12:00:29 PM","status":"Em Aberto"},{"printerSerial":"7421013003914","mensagem":"impressora carregada do Json","tipo":"impressora","timeStamp":"Jul 12, 2023, 12:06:07 PM","status":"Em Aberto"},{"printerSerial":"7421013003914","mensagem":"impressora carregada do Json","tipo":"impressora","timeStamp":"Jul 12, 2023, 12:12:05 PM","status":"Em Aberto"},{"printerSerial":"7421013003914","mensagem":"impressora carregada do Json","tipo":"impressora","timeStamp":"Jul 12, 2023, 12:12:49 PM","status":"Em Aberto"}]},{"name":"TÉCNICOS","marca":"Lexmark","modelo":"MX622adhe","status":"Online","url":"http://150.161.81.9","serial":"7018840002TH1","totalImpressoes":12589,"tonerObj":{"nivelToner":57,"statusToner":"OK","corToner":"Black","serialToner":"CAB200316DD9","pagRestantesToner":9500},"unidade":{"nivelUnidade":79,"corUnidade":"Black","serialUnidade":"CAD182623613","statusUnidade":"OK","pagRestantesUnidade":60000},"kitManutecao":{"pagRestantesKit":180100,"statuskit":"OK","serialKit":"LEX26F12610","nivelKit":94},"estilo":{"cssNivel":"progress-bar progress-bar-striped bg-info","cssKit":"progress-bar progress-bar-striped bg-success","cssUnidade":"progress-bar progress-bar-striped bg-success","cssName":"list-group-item list-group-item-success","cssStatusToner":"badge badge-success","cssStatusUnidade":"badge badge-success","cssStatusKit":"badge badge-success"},"ocorrencias":[]},{"name":"COMPRAS","marca":"Lexmark","modelo":"MX622adhe","status":"Online","url":"http://150.161.80.6","serial":"7018841002W8T","totalImpressoes":13682,"tonerObj":{"nivelToner":69,"statusToner":"OK","corToner":"Black","serialToner":"CAB2121638BC","pagRestantesToner":18800},"unidade":{"nivelUnidade":78,"corUnidade":"Black","serialUnidade":"CAD182783AB0","statusUnidade":"OK","pagRestantesUnidade":60000},"kitManutecao":{"pagRestantesKit":186400,"statuskit":"OK","serialKit":"LEX26F13740","nivelKit":94},"estilo":{"cssNivel":"progress-bar progress-bar-striped bg-info","cssKit":"progress-bar progress-bar-striped bg-success","cssUnidade":"progress-bar progress-bar-striped bg-success","cssName":"list-group-item list-group-item-success","cssStatusToner":"badge badge-success","cssStatusUnidade":"badge badge-success","cssStatusKit":"badge badge-success"},"ocorrencias":[]},{"name":"NAEPS","marca":"Lexmark","modelo":"MX622adhe","status":"Online","url":"http://150.161.81.10","serial":"7018841002W32","totalImpressoes":7130,"tonerObj":{"nivelToner":78,"statusToner":"OK","corToner":"Black","serialToner":"CAB220354856","pagRestantesToner":9000},"unidade":{"nivelUnidade":89,"corUnidade":"Black","serialUnidade":"CAD18278398F","statusUnidade":"OK","pagRestantesUnidade":60000},"kitManutecao":{"pagRestantesKit":200000,"statuskit":"OK","serialKit":"LEX26F7181","nivelKit":100},"estilo":{"cssNivel":"progress-bar progress-bar-striped bg-success","cssKit":"progress-bar progress-bar-striped bg-success","cssUnidade":"progress-bar progress-bar-striped bg-success","cssName":"list-group-item list-group-item-success","cssStatusToner":"badge badge-success","cssStatusUnidade":"badge badge-success","cssStatusKit":"badge badge-success"},"ocorrencias":[]},{"name":"NPE","marca":"Lexmark","modelo":"MX622adhe","status":"OffLine","url":"http://150.161.80.19","serial":"7018840002T9G","totalImpressoes":9285,"tonerObj":{"nivelToner":82,"statusToner":"OK","corToner":"Black","serialToner":"CAB1930804F4","pagRestantesToner":16000},"unidade":{"nivelUnidade":85,"corUnidade":"Black","serialUnidade":"CAD182535929","statusUnidade":"OK","pagRestantesUnidade":60000},"kitManutecao":{"pagRestantesKit":200000,"statuskit":"OK","serialKit":"LEX26F9340","nivelKit":100},"estilo":{"cssNivel":"progress-bar progress-bar-striped bg-success","cssKit":"progress-bar progress-bar-striped bg-success","cssUnidade":"progress-bar progress-bar-striped bg-success","cssName":"list-group-item list-group-item-danger","cssStatusToner":"badge badge-success","cssStatusUnidade":"badge badge-success","cssStatusKit":"badge badge-success"},"ocorrencias":[]},{"name":"SGC","marca":"Lexmark","modelo":"MX622adhe","status":"Online","url":"http://150.161.80.4","serial":"7018840002TFV","totalImpressoes":18810,"tonerObj":{"nivelToner":83,"statusToner":"OK","corToner":"Black","serialToner":"CAB211650D44","pagRestantesToner":21700},"unidade":{"nivelUnidade":69,"corUnidade":"Black","serialUnidade":"CAD182471165","statusUnidade":"OK","pagRestantesUnidade":60000},"kitManutecao":{"pagRestantesKit":174300,"statuskit":"OK","serialKit":"LEX26F18866","nivelKit":91},"estilo":{"cssNivel":"progress-bar progress-bar-striped bg-success","cssKit":"progress-bar progress-bar-striped bg-success","cssUnidade":"progress-bar progress-bar-striped bg-info","cssName":"list-group-item list-group-item-success","cssStatusToner":"badge badge-success","cssStatusUnidade":"badge badge-success","cssStatusKit":"badge badge-success"},"ocorrencias":[]},{"name":"NATI","marca":"Lexmark","modelo":"MX622adhe","status":"OffLine","url":"http://150.161.80.20","serial":"7018840002T7V","totalImpressoes":6510,"tonerObj":{"nivelToner":87,"statusToner":"OK","corToner":"Black","serialToner":"CAB220733390","pagRestantesToner":11800},"unidade":{"nivelUnidade":88,"corUnidade":"Black","serialUnidade":"CAD1825358DD","statusUnidade":"OK","pagRestantesUnidade":60000},"kitManutecao":{"pagRestantesKit":200000,"statuskit":"OK","serialKit":"LEX26F6518","nivelKit":100},"estilo":{"cssNivel":"progress-bar progress-bar-striped bg-success","cssKit":"progress-bar progress-bar-striped bg-success","cssUnidade":"progress-bar progress-bar-striped bg-success","cssName":"list-group-item list-group-item-danger","cssStatusToner":"badge badge-success","cssStatusUnidade":"badge badge-success","cssStatusKit":"badge badge-success"},"ocorrencias":[]},{"name":"EAD","marca":"Lexmark","modelo":"MX622adhe","status":"Online","url":"http://150.161.81.12","serial":"4600815002KZL","totalImpressoes":7231,"tonerObj":{"nivelToner":90,"statusToner":"OK","corToner":"Black","serialToner":"CAB19115617F","pagRestantesToner":19600},"unidade":{"nivelUnidade":88,"corUnidade":"Black","serialUnidade":"CAS180890AC7","statusUnidade":"OK","pagRestantesUnidade":60000},"kitManutecao":{"pagRestantesKit":200000,"statuskit":"OK","serialKit":"LEX26F7254","nivelKit":100},"estilo":{"cssNivel":"progress-bar progress-bar-striped bg-success","cssKit":"progress-bar progress-bar-striped bg-success","cssUnidade":"progress-bar progress-bar-striped bg-success","cssName":"list-group-item list-group-item-success","cssStatusToner":"badge badge-success","cssStatusUnidade":"badge badge-success","cssStatusKit":"badge badge-success"},"ocorrencias":[]},{"name":"ÉTICA","marca":"Lexmark","modelo":"MX622adhe","status":"Online","url":"http://150.161.81.11","serial":"7018840002T7T","totalImpressoes":5203,"tonerObj":{"nivelToner":100,"statusToner":"Abra a porta frontal.","corToner":"Black","serialToner":"CAB220680A6C","pagRestantesToner":-1},"unidade":{"nivelUnidade":92,"corUnidade":"Black","serialUnidade":"CAD182535894","statusUnidade":"OK","pagRestantesUnidade":60000},"kitManutecao":{"pagRestantesKit":200000,"statuskit":"OK","serialKit":"LEX26F5258","nivelKit":100},"estilo":{"cssNivel":"progress-bar progress-bar-striped bg-success","cssKit":"progress-bar progress-bar-striped bg-success","cssUnidade":"progress-bar progress-bar-striped bg-success","cssName":"list-group-item list-group-item-success","cssStatusToner":"badge badge-warning","cssStatusUnidade":"badge badge-success","cssStatusKit":"badge badge-success"},"ocorrencias":[]},{"nivelUnidadeCMY":100,"CssUnidadeCMY":"progress-bar progress-bar-striped bg-success","statusUnidadeCMY":"OK","corUnidadeCMY":"Color","pagRestantesUnidadeCMY":150000,"CssNivelUnidadeCMY":"progress-bar progress-bar-striped bg-success","serialUnidadeCMY":"CAH182051084","nivelTonerCyan":56,"cssNivelTonerCyan":"progress-bar progress-bar-striped bg-info","cssStatusTonerCyan":"badge badge-success","pagRestantesTonerCyan":7200,"statusTonerCyan":"OK","corTonerCyan":"Cyan","serialTonerCyan":"CAB213484A0C","nivelTonerMagenta":44,"cssNiveltonerMagenta":"progress-bar progress-bar-striped bg-warning","cssStatusTonerMagenta":"badge badge-success","pagRestantesTonerMagenta":5100,"statusTonerMagenta":"OK","corTonerMagenta":"Magenta","serialTonerMagenta":"CAB203185079","nivelTonerYellow":19,"cssNiveltonerYellow":"progress-bar progress-bar-striped bg-danger","cssStatusTonerYellow":"badge badge-success","pagRestantesTonerYellow":1900,"statusTonerYellow":"OK","corTonerYellow":"Yellow","serialTonerYellow":"CAB212182C6A","name":"DIRETORIA","marca":"Lexmark","modelo":"CX725","status":"Online","url":"http://150.161.80.21","serial":"75288310F2VBB","totalImpressoes":17507,"tonerObj":{"nivelToner":100,"statusToner":"OK","corToner":"Black","serialToner":"CAB2121143FA","pagRestantesToner":25000},"unidade":{"nivelUnidade":87,"corUnidade":"Black","serialUnidade":"CAH182041A2F","statusUnidade":"OK","pagRestantesUnidade":104000},"kitManutecao":{},"estilo":{"cssNivel":"progress-bar progress-bar-striped bg-success","cssUnidade":"progress-bar progress-bar-striped bg-success","cssName":"list-group-item list-group-item-success","cssStatusToner":"badge badge-success","cssStatusUnidade":"badge badge-success","cssStatusKit":"badge badge-warning"},"ocorrencias":[{"printerSerial":"75288310F2VBB","mensagem":"Impressora Carregada","tipo":"impressora","timeStamp":"Jul 12, 2023, 9:36:39 AM","status":"Em Aberto"},{"printerSerial":"75288310F2VBB","mensagem":"impressora carregada do Json","tipo":"impressora","timeStamp":"Jul 12, 2023, 9:37:49 AM","status":"Em Aberto"},{"printerSerial":"75288310F2VBB","mensagem":"impressora carregada do Json","tipo":"impressora","timeStamp":"Jul 12, 2023, 9:42:46 AM","status":"Em Aberto"},{"printerSerial":"75288310F2VBB","mensagem":"impressora carregada do Json","tipo":"impressora","timeStamp":"Jul 12, 2023, 9:44:03 AM","status":"Em Aberto"},{"printerSerial":"75288310F2VBB","mensagem":"impressora carregada do Json","tipo":"impressora","timeStamp":"Jul 12, 2023, 9:48:54 AM","status":"Em Aberto"},{"printerSerial":"75288310F2VBB","mensagem":"impressora carregada do Json","tipo":"impressora","timeStamp":"Jul 12, 2023, 9:50:11 AM","status":"Em Aberto"},{"printerSerial":"75288310F2VBB","mensagem":"impressora carregada do Json","tipo":"impressora","timeStamp":"Jul 12, 2023, 9:55:02 AM","status":"Em Aberto"},{"printerSerial":"75288310F2VBB","mensagem":"impressora carregada do Json","tipo":"impressora","timeStamp":"Jul 12, 2023, 9:56:18 AM","status":"Em Aberto"},{"printerSerial":"75288310F2VBB","mensagem":"impressora carregada do Json","tipo":"impressora","timeStamp":"Jul 12, 2023, 10:01:10 AM","status":"Em Aberto"},{"printerSerial":"75288310F2VBB","mensagem":"impressora carregada do Json","tipo":"impressora","timeStamp":"Jul 12, 2023, 10:02:26 AM","status":"Em Aberto"},{"printerSerial":"75288310F2VBB","mensagem":"impressora carregada do Json","tipo":"impressora","timeStamp":"Jul 12, 2023, 10:07:18 AM","status":"Em Aberto"},{"printerSerial":"75288310F2VBB","mensagem":"impressora carregada do Json","tipo":"impressora","timeStamp":"Jul 12, 2023, 10:08:34 AM","status":"Em Aberto"},{"printerSerial":"75288310F2VBB","mensagem":"impressora carregada do Json","tipo":"impressora","timeStamp":"Jul 12, 2023, 10:13:27 AM","status":"Em Aberto"},{"printerSerial":"75288310F2VBB","mensagem":"impressora carregada do Json","tipo":"impressora","timeStamp":"Jul 12, 2023, 10:14:42 AM","status":"Em Aberto"},{"printerSerial":"75288310F2VBB","mensagem":"impressora carregada do Json","tipo":"impressora","timeStamp":"Jul 12, 2023, 10:19:35 AM","status":"Em Aberto"},{"printerSerial":"75288310F2VBB","mensagem":"impressora carregada do Json","tipo":"impressora","timeStamp":"Jul 12, 2023, 10:20:08 AM","status":"Em Aberto"},{"printerSerial":"75288310F2VBB","mensagem":"impressora carregada do Json","tipo":"impressora","timeStamp":"Jul 12, 2023, 10:20:38 AM","status":"Em Aberto"},{"printerSerial":"75288310F2VBB","mensagem":"impressora carregada do Json","tipo":"impressora","timeStamp":"Jul 12, 2023, 10:20:53 AM","status":"Em Aberto"},{"printerSerial":"75288310F2VBB","mensagem":"impressora carregada do Json","tipo":"impressora","timeStamp":"Jul 12, 2023, 10:25:44 AM","status":"Em Aberto"},{"printerSerial":"75288310F2VBB","mensagem":"impressora carregada do Json","tipo":"impressora","timeStamp":"Jul 12, 2023, 10:27:00 AM","status":"Em Aberto"},{"printerSerial":"75288310F2VBB","mensagem":"impressora carregada do Json","tipo":"impressora","timeStamp":"Jul 12, 2023, 10:34:21 AM","status":"Em Aberto"},{"printerSerial":"75288310F2VBB","mensagem":"impressora carregada do Json","tipo":"impressora","timeStamp":"Jul 12, 2023, 10:35:02 AM","status":"Em Aberto"},{"printerSerial":"75288310F2VBB","mensagem":"impressora carregada do Json","tipo":"impressora","timeStamp":"Jul 12, 2023, 10:37:39 AM","status":"Em Aberto"},{"printerSerial":"75288310F2VBB","mensagem":"impressora carregada do Json","tipo":"impressora","timeStamp":"Jul 12, 2023, 10:38:57 AM","status":"Em Aberto"},{"printerSerial":"75288310F2VBB","mensagem":"impressora carregada do Json","tipo":"impressora","timeStamp":"Jul 12, 2023, 10:45:04 AM","status":"Em Aberto"},{"printerSerial":"75288310F2VBB","mensagem":"impressora carregada do Json","tipo":"impressora","timeStamp":"Jul 12, 2023, 10:49:44 AM","status":"Em Aberto"},{"printerSerial":"75288310F2VBB","mensagem":"impressora carregada do Json","tipo":"impressora","timeStamp":"Jul 12, 2023, 10:53:38 AM","status":"Em Aberto"},{"printerSerial":"75288310F2VBB","mensagem":"impressora carregada do Json","tipo":"impressora","timeStamp":"Jul 12, 2023, 10:55:20 AM","status":"Em Aberto"},{"printerSerial":"75288310F2VBB","mensagem":"impressora carregada do Json","tipo":"impressora","timeStamp":"Jul 12, 2023, 10:58:15 AM","status":"Em Aberto"},{"printerSerial":"75288310F2VBB","mensagem":"impressora carregada do Json","tipo":"impressora","timeStamp":"Jul 12, 2023, 10:58:23 AM","status":"Em Aberto"},{"printerSerial":"75288310F2VBB","mensagem":"impressora carregada do Json","tipo":"impressora","timeStamp":"Jul 12, 2023, 10:59:14 AM","status":"Em Aberto"},{"printerSerial":"75288310F2VBB","mensagem":"impressora carregada do Json","tipo":"impressora","timeStamp":"Jul 12, 2023, 11:05:21 AM","status":"Em Aberto"},{"printerSerial":"75288310F2VBB","mensagem":"impressora carregada do Json","tipo":"impressora","timeStamp":"Jul 12, 2023, 11:11:30 AM","status":"Em Aberto"},{"printerSerial":"75288310F2VBB","mensagem":"impressora carregada do Json","tipo":"impressora","timeStamp":"Jul 12, 2023, 11:17:38 AM","status":"Em Aberto"},{"printerSerial":"75288310F2VBB","mensagem":"impressora carregada do Json","tipo":"impressora","timeStamp":"Jul 12, 2023, 11:23:46 AM","status":"Em Aberto"},{"printerSerial":"75288310F2VBB","mensagem":"impressora carregada do Json","tipo":"impressora","timeStamp":"Jul 12, 2023, 11:29:54 AM","status":"Em Aberto"},{"printerSerial":"75288310F2VBB","mensagem":"impressora carregada do Json","tipo":"impressora","timeStamp":"Jul 12, 2023, 11:36:02 AM","status":"Em Aberto"},{"printerSerial":"75288310F2VBB","mensagem":"impressora carregada do Json","tipo":"impressora","timeStamp":"Jul 12, 2023, 11:42:10 AM","status":"Em Aberto"},{"printerSerial":"75288310F2VBB","mensagem":"impressora carregada do Json","tipo":"impressora","timeStamp":"Jul 12, 2023, 11:48:18 AM","status":"Em Aberto"},{"printerSerial":"75288310F2VBB","mensagem":"impressora carregada do Json","tipo":"impressora","timeStamp":"Jul 12, 2023, 11:54:26 AM","status":"Em Aberto"},{"printerSerial":"75288310F2VBB","mensagem":"impressora carregada do Json","tipo":"impressora","timeStamp":"Jul 12, 2023, 12:00:34 PM","status":"Em Aberto"},{"printerSerial":"75288310F2VBB","mensagem":"impressora carregada do Json","tipo":"impressora","timeStamp":"Jul 12, 2023, 12:06:12 PM","status":"Em Aberto"},{"printerSerial":"75288310F2VBB","mensagem":"impressora carregada do Json","tipo":"impressora","timeStamp":"Jul 12, 2023, 12:12:10 PM","status":"Em Aberto"},{"printerSerial":"75288310F2VBB","mensagem":"impressora carregada do Json","tipo":"impressora","timeStamp":"Jul 12, 2023, 12:12:54 PM","status":"Em Aberto"}]},{"name":"NACE","marca":"Lexmark","modelo":"MX622adhe","status":"OffLine","url":"http://150.161.80.22","serial":"7018841002W2V","totalImpressoes":0,"tonerObj":{},"unidade":{},"kitManutecao":{},"estilo":{"cssNivel":"progress-bar progress-bar-striped bg-danger","cssKit":"progress-bar progress-bar-striped bg-danger","cssUnidade":"progress-bar progress-bar-striped bg-danger","cssName":"list-group-item list-group-item-danger","cssStatusToner":"badge badge-warning","cssStatusUnidade":"badge badge-warning","cssStatusKit":"badge badge-warning"},"ocorrencias":[{"printerSerial":"7018841002W2V","mensagem":"Impressora Carregada","tipo":"impressora","timeStamp":"Jul 12, 2023, 9:36:39 AM","status":"Em Aberto"}]},{"name":"SEGURANÇA_ANEXO","marca":"Lexmark","modelo":"MX622adhe","status":"OffLine","url":"http://150.161.81.13","serial":"sfsdfsdfsdfs","totalImpressoes":0,"tonerObj":{},"unidade":{},"kitManutecao":{},"estilo":{"cssNivel":"progress-bar progress-bar-striped bg-danger","cssKit":"progress-bar progress-bar-striped bg-danger","cssUnidade":"progress-bar progress-bar-striped bg-danger","cssName":"list-group-item list-group-item-danger","cssStatusToner":"badge badge-warning","cssStatusUnidade":"badge badge-warning","cssStatusKit":"badge badge-warning"},"ocorrencias":[{"printerSerial":"sfsdfsdfsdfs","mensagem":"Impressora Carregada","tipo":"impressora","timeStamp":"Jul 12, 2023, 9:36:39 AM","status":"Em Aberto"}]},{"name":"HALL","marca":"Lexmark","modelo":"MX622adhe","status":"OffLine","url":"http://150.161.80.11","serial":"7018841002VG4","totalImpressoes":0,"tonerObj":{},"unidade":{},"kitManutecao":{},"estilo":{"cssNivel":"progress-bar progress-bar-striped bg-danger","cssKit":"progress-bar progress-bar-striped bg-danger","cssUnidade":"progress-bar progress-bar-striped bg-danger","cssName":"list-group-item list-group-item-danger","cssStatusToner":"badge badge-warning","cssStatusUnidade":"badge badge-warning","cssStatusKit":"badge badge-warning"},"ocorrencias":[{"printerSerial":"7018841002VG4","mensagem":"Impressora Carregada","tipo":"impressora","timeStamp":"Jul 12, 2023, 9:36:39 AM","status":"Em Aberto"}]}]}